funcportal/__init__.py
funcportal/app.py
funcportal/cli.py
funcportal/function.py
funcportal/handler.py
funcportal/util.py
funcportal/version.py
funcportal-0.2.0.dist-info/METADATA
funcportal-0.2.0.dist-info/RECORD
funcportal-0.2.0.dist-info/WHEEL
funcportal-0.2.0.dist-info/entry_points.txt
funcportal-0.2.0.dist-info/top_level.txt
