Metadata-Version: 2.1
Name: funcportal
Version: 0.2.0
Summary: Serve Python functions as web APIs
Home-page: UNKNOWN
Author: UNKNOWN
Author-email: UNKNOWN
License: UNKNOWN
Platform: UNKNOWN
Requires-Dist: flask
Requires-Dist: requests
Requires-Dist: six
Requires-Dist: pyyaml
Requires-Dist: rq
Requires-Dist: redis
